ulsid/__init__.py
ulsid/access.py
ulsid/analyse.py
ulsid/exceptions.py
ulsid/generate.py
ulsid-0.0.2.dist-info/LICENSE
ulsid-0.0.2.dist-info/METADATA
ulsid-0.0.2.dist-info/WHEEL
ulsid-0.0.2.dist-info/top_level.txt
ulsid-0.0.2.dist-info/RECORD
